Exscript/__init__.py
Exscript/account.py
Exscript/host.py
Exscript/key.py
Exscript/logger.py
Exscript/queue.py
Exscript/version.py
Exscript/emulators/__init__.py
Exscript/emulators/command.py
Exscript/emulators/iosemu.py
Exscript/emulators/vdevice.py
Exscript/interpreter/__init__.py
Exscript/interpreter/append.py
Exscript/interpreter/assign.py
Exscript/interpreter/code.py
Exscript/interpreter/enter.py
Exscript/interpreter/exception.py
Exscript/interpreter/execute.py
Exscript/interpreter/expression.py
Exscript/interpreter/extract.py
Exscript/interpreter/fail.py
Exscript/interpreter/functioncall.py
Exscript/interpreter/ifcondition.py
Exscript/interpreter/loop.py
Exscript/interpreter/number.py
Exscript/interpreter/parser.py
Exscript/interpreter/program.py
Exscript/interpreter/regex.py
Exscript/interpreter/scope.py
Exscript/interpreter/string.py
Exscript/interpreter/template.py
Exscript/interpreter/term.py
Exscript/interpreter/trying.py
Exscript/interpreter/variable.py
Exscript/parselib/__init__.py
Exscript/parselib/exception.py
Exscript/parselib/lexer.py
Exscript/parselib/token.py
Exscript/protocols/__init__.py
Exscript/protocols/dummy.py
Exscript/protocols/exception.py
Exscript/protocols/osguesser.py
Exscript/protocols/protocol.py
Exscript/protocols/ssh2.py
Exscript/protocols/telnet.py
Exscript/protocols/telnetlib.py
Exscript/protocols/drivers/__init__.py
Exscript/protocols/drivers/ace.py
Exscript/protocols/drivers/adtran.py
Exscript/protocols/drivers/aironet.py
Exscript/protocols/drivers/aix.py
Exscript/protocols/drivers/arbor_peakflow.py
Exscript/protocols/drivers/aruba.py
Exscript/protocols/drivers/bigip.py
Exscript/protocols/drivers/brocade.py
Exscript/protocols/drivers/cienasaos.py
Exscript/protocols/drivers/driver.py
Exscript/protocols/drivers/enterasys.py
Exscript/protocols/drivers/enterasys_wc.py
Exscript/protocols/drivers/eos.py
Exscript/protocols/drivers/ericsson_ban.py
Exscript/protocols/drivers/fortios.py
Exscript/protocols/drivers/generic.py
Prov_Exscript-2.0.dist-info/AUTHORS
Prov_Exscript-2.0.dist-info/COPYING
Prov_Exscript-2.0.dist-info/METADATA
Prov_Exscript-2.0.dist-info/WHEEL
Prov_Exscript-2.0.dist-info/top_level.txt
Prov_Exscript-2.0.dist-info/RECORD
