Metadata-Version: 2.1
Name: Prov_Exscript
Version: 2.0
Summary: Automating Telnet and SSH
Home-page: https://github.com/Prov-RafaelSavoy/prov_exscript/
Author: Samuel Abels
Author-email: knipknap@gmail.com
License: MIT
Keywords: prov_exscript telnet ssh network networking automate automation library
Classifier: Development Status :: 5 - Production/Stable
Classifier: Intended Audience :: Developers
Classifier: License :: OSI Approved :: MIT License
Classifier: Programming Language :: Python
Classifier: Topic :: Security
Classifier: Topic :: Software Development :: Libraries
Classifier: Topic :: Software Development :: Libraries :: Python Modules
License-File: COPYING
License-File: AUTHORS
Requires-Dist: future
Requires-Dist: configparser
Requires-Dist: paramiko
Requires-Dist: pycryptodomex
